haystack_integrations/components/embedders/py.typed
haystack_integrations/components/embedders/optimum/__init__.py
haystack_integrations/components/embedders/optimum/_backend.py
haystack_integrations/components/embedders/optimum/optimization.py
haystack_integrations/components/embedders/optimum/optimum_document_embedder.py
haystack_integrations/components/embedders/optimum/optimum_text_embedder.py
haystack_integrations/components/embedders/optimum/pooling.py
haystack_integrations/components/embedders/optimum/quantization.py
optimum_haystack-2.0.0.dist-info/METADATA
optimum_haystack-2.0.0.dist-info/WHEEL
optimum_haystack-2.0.0.dist-info/licenses/LICENSE.txt
optimum_haystack-2.0.0.dist-info/RECORD
