Metadata-Version: 2.4
Name: optimum-haystack
Version: 2.0.0
Summary: Component to embed strings and Documents using models loaded with the HuggingFace Optimum library. This component is designed to seamlessly inference models using the high speed ONNX runtime.
Project-URL: Documentation, https://github.com/deepset-ai/haystack-core-integrations/tree/main/integrations/optimum#readme
Project-URL: Issues, https://github.com/deepset-ai/haystack-core-integrations/issues
Project-URL: Source, https://github.com/deepset-ai/haystack-core-integrations/tree/main/integrations/optimum
Author: Ashwin Mathur
Author-email: deepset GmbH <info@deepset.ai>
License-Expression: Apache-2.0
License-File: LICENSE.txt
Classifier: Development Status :: 4 - Beta
Classifier: License :: OSI Approved :: Apache Software License
Classifier: Programming Language :: Python
Classifier: Programming Language :: Python :: 3.10
Classifier: Programming Language :: Python :: 3.11
Classifier: Programming Language :: Python :: 3.12
Classifier: Programming Language :: Python :: Implementation :: CPython
Classifier: Programming Language :: Python :: Implementation :: PyPy
Requires-Python: >=3.10
Requires-Dist: haystack-ai>=2.22.0
Requires-Dist: optimum[onnxruntime]>=1.21.0
Requires-Dist: sentence-transformers>=2.3
Requires-Dist: tokenizers>=0.20.2
